{
  "slug": "cupra",
  "name": "CUPRA",
  "country": "España",
  "founded": "2018",
  "hq": "Martorell, España",
  "description": "CUPRA es la marca deportiva del grupo SEAT, creada en 2018 como marca independiente. Con sede en Martorell (Barcelona), combina el diseño español con rendimiento deportivo y tecnología de vanguardia en modelos como el Formentor y el Born.",
  "modelCount": 6,
  "publishedAt": null,
  "models": [
    {
      "slug": "formentor",
      "name": "Formentor",
      "bodyType": "SUV Coupé",
      "segment": "Compacto",
      "years": "2020-2026",
      "current": true,
      "publishedAt": null,
      "generations": [
        {
          "slug": "2020-2026",
          "name": "Generación actual (2020-2026)",
          "yearStart": 2020,
          "yearEnd": 2026,
          "publishedAt": null,
          "variants": [
            {
              "slug": "1-6-hev-143-cv",
              "name": "1.6 HEV 143 CV",
              "engineCode": "",
              "displacement": 1598,
              "fuelType": "Híbrido",
              "powerHp": 143,
              "powerKw": 105,
              "torqueNm": 253,
              "transmission": "Automático eCVT",
              "gears": 0,
              "driveType": "FWD",
              "lengthMm": 4278,
              "widthMm": 1815,
              "heightMm": 1522,
              "wheelbaseMm": 2637,
              "weightKg": 1439,
              "grossWeightKg": 1897,
              "trunkCapacityL": 479,
              "fuelTankL": 54,
              "consumption": 4.1,
              "co2": 105,
              "topSpeed": 200,
              "acceleration0100": 11.0,
              "tireSizeFront": "205/55 R16",
              "tireSizeRear": "205/55 R16",
              "rimSize": "6.5Jx16 ET35",
              "pcd": "5x108",
              "centerBore": 57.1,
              "offsetMin": 43,
              "offsetMax": 52,
              "wheelTorqueNm": 140,
              "threadSize": "M14x1.5",
              "boltType": "Tornillo",
              "tirePressureFrontBar": 2.1,
              "tirePressureRearBar": 2.4,
              "tirePressureFrontLoadedBar": 2.6,
              "tirePressureRearLoadedBar": 2.8,
              "publishedAt": null
            },
            {
              "slug": "1-8-hybrid-122-cv",
              "name": "1.8 Hybrid 122 CV",
              "engineCode": "",
              "displacement": 1798,
              "fuelType": "Híbrido",
              "powerHp": 122,
              "powerKw": 90,
              "torqueNm": 142,
              "transmission": "Automático CVT",
              "gears": 0,
              "driveType": "FWD",
              "lengthMm": 4372,
              "widthMm": 1816,
              "heightMm": 1462,
              "wheelbaseMm": 2697,
              "weightKg": 1371,
              "grossWeightKg": 1610,
              "trunkCapacityL": 411,
              "fuelTankL": 50,
              "consumption": 4.8,
              "co2": 103,
              "topSpeed": 215,
              "acceleration0100": 6.7,
              "tireSizeFront": "205/55 R16",
              "tireSizeRear": "205/55 R16",
              "rimSize": "6.5Jx16 ET48",
              "pcd": "5x108",
              "centerBore": 57.1,
              "offsetMin": 39,
              "offsetMax": 53,
              "wheelTorqueNm": 103,
              "threadSize": "M12x1.5",
              "boltType": "Tornillo",
              "tirePressureFrontBar": 2.4,
              "tirePressureRearBar": 2.4,
              "tirePressureFrontLoadedBar": 2.4,
              "tirePressureRearLoadedBar": 2.3,
              "publishedAt": null
            },
            {
              "slug": "2-0-tsi-190-cv",
              "name": "2.0 TSI 190 CV",
              "engineCode": "",
              "displacement": 1984,
              "fuelType": "Gasolina",
              "powerHp": 190,
              "powerKw": 140,
              "torqueNm": 320,
              "transmission": "Automático DSG 7v",
              "gears": 7,
              "driveType": "FWD",
              "lengthMm": 4493,
              "widthMm": 1791,
              "heightMm": 1472,
              "wheelbaseMm": 2678,
              "weightKg": 1337,
              "grossWeightKg": 1940,
              "trunkCapacityL": 472,
              "fuelTankL": 51,
              "consumption": 7.2,
              "co2": 161,
              "topSpeed": 191,
              "acceleration0100": 12.2,
              "tireSizeFront": "205/55 R16",
              "tireSizeRear": "205/55 R16",
              "rimSize": "6.5Jx16 ET50",
              "pcd": "5x108",
              "centerBore": 57.1,
              "offsetMin": 39,
              "offsetMax": 48,
              "wheelTorqueNm": 140,
              "threadSize": "M12x1.25",
              "boltType": "Tornillo",
              "tirePressureFrontBar": 2.0,
              "tirePressureRearBar": 2.5,
              "tirePressureFrontLoadedBar": 2.4,
              "tirePressureRearLoadedBar": 2.4,
              "publishedAt": null
            },
            {
              "slug": "2-0-tfsi-245-cv",
              "name": "2.0 TFSI 245 CV",
              "engineCode": "",
              "displacement": 1984,
              "fuelType": "Gasolina",
              "powerHp": 245,
              "powerKw": 180,
              "torqueNm": 370,
              "transmission": "Automático S tronic 7v",
              "gears": 7,
              "driveType": "FWD",
              "lengthMm": 4240,
              "widthMm": 1798,
              "heightMm": 1446,
              "wheelbaseMm": 2660,
              "weightKg": 1362,
              "grossWeightKg": 1893,
              "trunkCapacityL": 364,
              "fuelTankL": 46,
              "consumption": 7.6,
              "co2": 182,
              "topSpeed": 233,
              "acceleration0100": 9.6,
              "tireSizeFront": "205/55 R16",
              "tireSizeRear": "205/55 R16",
              "rimSize": "6.5Jx16 ET49",
              "pcd": "5x108",
              "centerBore": 57.1,
              "offsetMin": 38,
              "offsetMax": 48,
              "wheelTorqueNm": 120,
              "threadSize": "M12x1.5",
              "boltType": "Tuerca",
              "tirePressureFrontBar": 2.3,
              "tirePressureRearBar": 2.5,
              "tirePressureFrontLoadedBar": 2.5,
              "tirePressureRearLoadedBar": 2.6,
              "publishedAt": null
            }
          ]
        }
      ],
      "imageUrl": "https://upload.wikimedia.org/wikipedia/commons/thumb/9/9f/Cupra_Formentor_IMG_9668.jpg/1280px-Cupra_Formentor_IMG_9668.jpg",
      "imagePageUrl": "https://en.wikipedia.org/wiki/Cupra_Formentor",
      "imageTitle": "Cupra Formentor",
      "imageLicense": "CC BY-SA / Wikimedia Commons (via Wikipedia page images)",
      "imageFetchedAt": "2026-04-01",
      "wheelSizeKnown": true
    },
    {
      "slug": "born",
      "name": "Born",
      "bodyType": "Hatchback",
      "segment": "Compacto",
      "years": "2021-2026",
      "current": true,
      "publishedAt": null,
      "generations": [
        {
          "slug": "2021-2026",
          "name": "Generación actual (2021-2026)",
          "yearStart": 2021,
          "yearEnd": 2026,
          "publishedAt": null,
          "variants": [
            {
              "slug": "electric-204-cv",
              "name": "Electric 204 CV",
              "engineCode": "",
              "displacement": 0,
              "fuelType": "Eléctrico",
              "powerHp": 204,
              "powerKw": 150,
              "torqueNm": 310,
              "transmission": "Automático 1v",
              "gears": 1,
              "driveType": "FWD",
              "lengthMm": 4304,
              "widthMm": 1806,
              "heightMm": 1441,
              "wheelbaseMm": 2633,
              "weightKg": 1279,
              "grossWeightKg": 1551,
              "trunkCapacityL": 353,
              "fuelTankL": 0,
              "consumption": 17.1,
              "co2": 0,
              "topSpeed": 204,
              "acceleration0100": 11.6,
              "tireSizeFront": "205/60 R16",
              "tireSizeRear": "205/60 R16",
              "rimSize": "6.5Jx16 ET44",
              "pcd": "5x108",
              "centerBore": 60.1,
              "offsetMin": 39,
              "offsetMax": 50,
              "wheelTorqueNm": 130,
              "threadSize": "M14x1.5",
              "boltType": "Tornillo",
              "tirePressureFrontBar": 2.4,
              "tirePressureRearBar": 2.4,
              "tirePressureFrontLoadedBar": 2.5,
              "tirePressureRearLoadedBar": 2.7,
              "publishedAt": null
            },
            {
              "slug": "electric-408-cv-awd",
              "name": "Electric 408 CV AWD",
              "engineCode": "",
              "displacement": 0,
              "fuelType": "Eléctrico",
              "powerHp": 408,
              "powerKw": 300,
              "torqueNm": 545,
              "transmission": "Automático 1v",
              "gears": 1,
              "driveType": "FWD",
              "lengthMm": 4237,
              "widthMm": 1845,
              "heightMm": 1482,
              "wheelbaseMm": 2601,
              "weightKg": 1432,
              "grossWeightKg": 1827,
              "trunkCapacityL": 438,
              "fuelTankL": 0,
              "consumption": 20.0,
              "co2": 0,
              "topSpeed": 167,
              "acceleration0100": 11.6,
              "tireSizeFront": "205/60 R16",
              "tireSizeRear": "205/60 R16",
              "rimSize": "6.5Jx16 ET47",
              "pcd": "5x108",
              "centerBore": 60.1,
              "offsetMin": 39,
              "offsetMax": 53,
              "wheelTorqueNm": 120,
              "threadSize": "M12x1.5",
              "boltType": "Tornillo",
              "tirePressureFrontBar": 2.0,
              "tirePressureRearBar": 2.2,
              "tirePressureFrontLoadedBar": 2.4,
              "tirePressureRearLoadedBar": 2.4,
              "publishedAt": null
            }
          ]
        }
      ],
      "imageUrl": "https://upload.wikimedia.org/wikipedia/commons/thumb/7/75/Cupra_Born_IMG_8234.jpg/1280px-Cupra_Born_IMG_8234.jpg",
      "imagePageUrl": "https://en.wikipedia.org/wiki/Cupra_Born",
      "imageTitle": "Cupra Born",
      "imageLicense": "CC BY-SA / Wikimedia Commons (via Wikipedia page images)",
      "imageFetchedAt": "2026-04-01",
      "wheelSizeKnown": true
    },
    {
      "slug": "leon",
      "name": "Leon",
      "bodyType": "Hatchback/Familiar",
      "segment": "Compacto",
      "years": "2020-2026",
      "current": true,
      "publishedAt": null,
      "generations": [
        {
          "slug": "2020-2026",
          "name": "Generación actual (2020-2026)",
          "yearStart": 2020,
          "yearEnd": 2026,
          "publishedAt": null,
          "variants": [
            {
              "slug": "2-0-tdi-200-cv",
              "name": "2.0 TDI 200 CV",
              "engineCode": "",
              "displacement": 1968,
              "fuelType": "Diésel",
              "powerHp": 200,
              "powerKw": 147,
              "torqueNm": 400,
              "transmission": "Automático DSG 7v",
              "gears": 7,
              "driveType": "FWD",
              "lengthMm": 4273,
              "widthMm": 1807,
              "heightMm": 1501,
              "wheelbaseMm": 2639,
              "weightKg": 1337,
              "grossWeightKg": 1693,
              "trunkCapacityL": 395,
              "fuelTankL": 53,
              "consumption": 5.4,
              "co2": 145,
              "topSpeed": 247,
              "acceleration0100": 11.3,
              "tireSizeFront": "215/45 R17",
              "tireSizeRear": "215/45 R17",
              "rimSize": "6.5Jx17 ET39",
              "pcd": "5x114.3",
              "centerBore": 56.1,
              "offsetMin": 41,
              "offsetMax": 53,
              "wheelTorqueNm": 140,
              "threadSize": "M12x1.5",
              "boltType": "Tuerca",
              "tirePressureFrontBar": 2.3,
              "tirePressureRearBar": 2.1,
              "tirePressureFrontLoadedBar": 2.4,
              "tirePressureRearLoadedBar": 2.3,
              "publishedAt": null
            },
            {
              "slug": "1-6-hev-143-cv",
              "name": "1.6 HEV 143 CV",
              "engineCode": "",
              "displacement": 1598,
              "fuelType": "Híbrido",
              "powerHp": 143,
              "powerKw": 105,
              "torqueNm": 253,
              "transmission": "Automático eCVT",
              "gears": 0,
              "driveType": "FWD",
              "lengthMm": 4484,
              "widthMm": 1848,
              "heightMm": 1450,
              "wheelbaseMm": 2685,
              "weightKg": 1370,
              "grossWeightKg": 1608,
              "trunkCapacityL": 422,
              "fuelTankL": 53,
              "consumption": 4.4,
              "co2": 97,
              "topSpeed": 247,
              "acceleration0100": 9.3,
              "tireSizeFront": "215/45 R17",
              "tireSizeRear": "215/45 R17",
              "rimSize": "6.5Jx17 ET42",
              "pcd": "5x114.3",
              "centerBore": 56.1,
              "offsetMin": 41,
              "offsetMax": 49,
              "wheelTorqueNm": 140,
              "threadSize": "M12x1.5",
              "boltType": "Tornillo",
              "tirePressureFrontBar": 2.3,
              "tirePressureRearBar": 2.3,
              "tirePressureFrontLoadedBar": 2.3,
              "tirePressureRearLoadedBar": 2.7,
              "publishedAt": null
            },
            {
              "slug": "1-5-mhev-130-cv",
              "name": "1.5 MHEV 130 CV",
              "engineCode": "",
              "displacement": 1498,
              "fuelType": "Híbrido",
              "powerHp": 130,
              "powerKw": 96,
              "torqueNm": 230,
              "transmission": "Automático DCT 7v",
              "gears": 7,
              "driveType": "FWD",
              "lengthMm": 4220,
              "widthMm": 1848,
              "heightMm": 1487,
              "wheelbaseMm": 2650,
              "weightKg": 1278,
              "grossWeightKg": 1693,
              "trunkCapacityL": 386,
              "fuelTankL": 51,
              "consumption": 5.2,
              "co2": 117,
              "topSpeed": 164,
              "acceleration0100": 10.4,
              "tireSizeFront": "215/45 R17",
              "tireSizeRear": "215/45 R17",
              "rimSize": "6.5Jx17 ET36",
              "pcd": "5x114.3",
              "centerBore": 56.1,
              "offsetMin": 41,
              "offsetMax": 47,
              "wheelTorqueNm": 120,
              "threadSize": "M14x1.5",
              "boltType": "Tornillo",
              "tirePressureFrontBar": 2.4,
              "tirePressureRearBar": 2.0,
              "tirePressureFrontLoadedBar": 2.6,
              "tirePressureRearLoadedBar": 2.6,
              "publishedAt": null
            },
            {
              "slug": "1-2-puretech-130-cv",
              "name": "1.2 PureTech 130 CV",
              "engineCode": "",
              "displacement": 1199,
              "fuelType": "Gasolina",
              "powerHp": 130,
              "powerKw": 96,
              "torqueNm": 230,
              "transmission": "Automático 8v",
              "gears": 8,
              "driveType": "FWD",
              "lengthMm": 4375,
              "widthMm": 1800,
              "heightMm": 1451,
              "wheelbaseMm": 2688,
              "weightKg": 1302,
              "grossWeightKg": 1759,
              "trunkCapacityL": 396,
              "fuelTankL": 51,
              "consumption": 6.1,
              "co2": 133,
              "topSpeed": 237,
              "acceleration0100": 10.2,
              "tireSizeFront": "215/45 R17",
              "tireSizeRear": "215/45 R17",
              "rimSize": "6.5Jx17 ET47",
              "pcd": "5x114.3",
              "centerBore": 56.1,
              "offsetMin": 38,
              "offsetMax": 48,
              "wheelTorqueNm": 110,
              "threadSize": "M12x1.5",
              "boltType": "Tornillo",
              "tirePressureFrontBar": 2.3,
              "tirePressureRearBar": 2.1,
              "tirePressureFrontLoadedBar": 2.5,
              "tirePressureRearLoadedBar": 2.5,
              "publishedAt": null
            },
            {
              "slug": "1-0-tsi-95-cv",
              "name": "1.0 TSI 95 CV",
              "engineCode": "",
              "displacement": 999,
              "fuelType": "Gasolina",
              "powerHp": 95,
              "powerKw": 70,
              "torqueNm": 175,
              "transmission": "Manual 5v",
              "gears": 5,
              "driveType": "FWD",
              "lengthMm": 4403,
              "widthMm": 1844,
              "heightMm": 1450,
              "wheelbaseMm": 2685,
              "weightKg": 1453,
              "grossWeightKg": 1793,
              "trunkCapacityL": 392,
              "fuelTankL": 49,
              "consumption": 5.3,
              "co2": 121,
              "topSpeed": 214,
              "acceleration0100": 11.3,
              "tireSizeFront": "215/45 R17",
              "tireSizeRear": "215/45 R17",
              "rimSize": "6.5Jx17 ET48",
              "pcd": "5x114.3",
              "centerBore": 56.1,
              "offsetMin": 40,
              "offsetMax": 53,
              "wheelTorqueNm": 103,
              "threadSize": "M12x1.5",
              "boltType": "Tornillo",
              "tirePressureFrontBar": 2.4,
              "tirePressureRearBar": 2.2,
              "tirePressureFrontLoadedBar": 2.5,
              "tirePressureRearLoadedBar": 2.6,
              "publishedAt": null
            }
          ]
        }
      ],
      "imageUrl": "https://upload.wikimedia.org/wikipedia/commons/thumb/2/24/2020_SEAT_Leon_FR_TSi_Evo_1.5_Front.jpg/1280px-2020_SEAT_Leon_FR_TSi_Evo_1.5_Front.jpg",
      "imagePageUrl": "https://en.wikipedia.org/wiki/SEAT_Le%C3%B3n",
      "imageTitle": "SEAT León",
      "imageLicense": "CC BY-SA / Wikimedia Commons (via Wikipedia page images)",
      "imageFetchedAt": "2026-04-01",
      "wheelSizeKnown": true
    },
    {
      "slug": "terramar",
      "name": "Terramar",
      "bodyType": "SUV",
      "segment": "Medio",
      "years": "2024-2026",
      "current": true,
      "publishedAt": null,
      "generations": [
        {
          "slug": "2024-2026",
          "name": "Generación actual (2024-2026)",
          "yearStart": 2024,
          "yearEnd": 2026,
          "publishedAt": null,
          "variants": [
            {
              "slug": "1-2-puretech-130-cv",
              "name": "1.2 PureTech 130 CV",
              "engineCode": "",
              "displacement": 1199,
              "fuelType": "Gasolina",
              "powerHp": 130,
              "powerKw": 96,
              "torqueNm": 230,
              "transmission": "Automático 8v",
              "gears": 8,
              "driveType": "FWD",
              "lengthMm": 4806,
              "widthMm": 1876,
              "heightMm": 1491,
              "wheelbaseMm": 2837,
              "weightKg": 1653,
              "grossWeightKg": 1849,
              "trunkCapacityL": 456,
              "fuelTankL": 56,
              "consumption": 5.8,
              "co2": 128,
              "topSpeed": 219,
              "acceleration0100": 10.7,
              "tireSizeFront": "235/45 R18",
              "tireSizeRear": "235/45 R18",
              "rimSize": "6.5Jx18 ET39",
              "pcd": "5x108",
              "centerBore": 66.6,
              "offsetMin": 35,
              "offsetMax": 40,
              "wheelTorqueNm": 103,
              "threadSize": "M12x1.5",
              "boltType": "Tornillo",
              "tirePressureFrontBar": 2.2,
              "tirePressureRearBar": 2.4,
              "tirePressureFrontLoadedBar": 2.3,
              "tirePressureRearLoadedBar": 2.4,
              "publishedAt": null
            },
            {
              "slug": "2-0-tdi-150-cv",
              "name": "2.0 TDI 150 CV",
              "engineCode": "",
              "displacement": 1968,
              "fuelType": "Diésel",
              "powerHp": 150,
              "powerKw": 110,
              "torqueNm": 360,
              "transmission": "Manual 6v",
              "gears": 6,
              "driveType": "FWD",
              "lengthMm": 4708,
              "widthMm": 1835,
              "heightMm": 1493,
              "wheelbaseMm": 2803,
              "weightKg": 1704,
              "grossWeightKg": 2068,
              "trunkCapacityL": 535,
              "fuelTankL": 65,
              "consumption": 5.2,
              "co2": 134,
              "topSpeed": 163,
              "acceleration0100": 6.9,
              "tireSizeFront": "235/45 R18",
              "tireSizeRear": "235/45 R18",
              "rimSize": "6.5Jx18 ET46",
              "pcd": "5x108",
              "centerBore": 66.6,
              "offsetMin": 40,
              "offsetMax": 46,
              "wheelTorqueNm": 120,
              "threadSize": "M14x1.5",
              "boltType": "Tuerca",
              "tirePressureFrontBar": 2.1,
              "tirePressureRearBar": 2.3,
              "tirePressureFrontLoadedBar": 2.4,
              "tirePressureRearLoadedBar": 2.6,
              "publishedAt": null
            },
            {
              "slug": "3-0-d-286-cv",
              "name": "3.0 d 286 CV",
              "engineCode": "",
              "displacement": 2993,
              "fuelType": "Diésel",
              "powerHp": 286,
              "powerKw": 210,
              "torqueNm": 650,
              "transmission": "Automático 8v",
              "gears": 8,
              "driveType": "FWD",
              "lengthMm": 4637,
              "widthMm": 1853,
              "heightMm": 1573,
              "wheelbaseMm": 2746,
              "weightKg": 1692,
              "grossWeightKg": 1993,
              "trunkCapacityL": 494,
              "fuelTankL": 57,
              "consumption": 6.9,
              "co2": 184,
              "topSpeed": 224,
              "acceleration0100": 6.8,
              "tireSizeFront": "235/45 R18",
              "tireSizeRear": "235/45 R18",
              "rimSize": "6.5Jx18 ET36",
              "pcd": "5x108",
              "centerBore": 66.6,
              "offsetMin": 40,
              "offsetMax": 46,
              "wheelTorqueNm": 103,
              "threadSize": "M14x1.5",
              "boltType": "Tornillo",
              "tirePressureFrontBar": 2.1,
              "tirePressureRearBar": 2.1,
              "tirePressureFrontLoadedBar": 2.6,
              "tirePressureRearLoadedBar": 2.7,
              "publishedAt": null
            }
          ]
        }
      ],
      "imageUrl": "https://upload.wikimedia.org/wikipedia/commons/thumb/8/8b/Cupra_Terramar_VZ_DSC_8241.jpg/1280px-Cupra_Terramar_VZ_DSC_8241.jpg",
      "imagePageUrl": "https://en.wikipedia.org/wiki/Cupra_Terramar",
      "imageTitle": "Cupra Terramar",
      "imageLicense": "CC BY-SA / Wikimedia Commons (via Wikipedia page images)",
      "imageFetchedAt": "2026-04-01",
      "wheelSizeKnown": true
    },
    {
      "slug": "tavascan",
      "name": "Tavascan",
      "bodyType": "SUV Coupé",
      "segment": "Medio",
      "years": "2024-2026",
      "current": true,
      "publishedAt": null,
      "generations": [
        {
          "slug": "2024-2026",
          "name": "Generación actual (2024-2026)",
          "yearStart": 2024,
          "yearEnd": 2026,
          "publishedAt": null,
          "variants": [
            {
              "slug": "2-0-tdi-200-cv",
              "name": "2.0 TDI 200 CV",
              "engineCode": "",
              "displacement": 1968,
              "fuelType": "Diésel",
              "powerHp": 200,
              "powerKw": 147,
              "torqueNm": 400,
              "transmission": "Automático DSG 7v",
              "gears": 7,
              "driveType": "FWD",
              "lengthMm": 4817,
              "widthMm": 1844,
              "heightMm": 1581,
              "wheelbaseMm": 2740,
              "weightKg": 1512,
              "grossWeightKg": 2200,
              "trunkCapacityL": 494,
              "fuelTankL": 63,
              "consumption": 5.7,
              "co2": 141,
              "topSpeed": 181,
              "acceleration0100": 11.0,
              "tireSizeFront": "225/55 R17",
              "tireSizeRear": "225/55 R17",
              "rimSize": "6.5Jx17 ET42",
              "pcd": "5x112",
              "centerBore": 72.6,
              "offsetMin": 36,
              "offsetMax": 44,
              "wheelTorqueNm": 140,
              "threadSize": "M12x1.5",
              "boltType": "Tornillo",
              "tirePressureFrontBar": 2.1,
              "tirePressureRearBar": 2.2,
              "tirePressureFrontLoadedBar": 2.7,
              "tirePressureRearLoadedBar": 2.7,
              "publishedAt": null
            },
            {
              "slug": "1-6-cdti-136-cv",
              "name": "1.6 CDTi 136 CV",
              "engineCode": "",
              "displacement": 1598,
              "fuelType": "Diésel",
              "powerHp": 136,
              "powerKw": 100,
              "torqueNm": 320,
              "transmission": "Automático 8v",
              "gears": 8,
              "driveType": "FWD",
              "lengthMm": 4730,
              "widthMm": 1855,
              "heightMm": 1684,
              "wheelbaseMm": 2824,
              "weightKg": 1645,
              "grossWeightKg": 1897,
              "trunkCapacityL": 537,
              "fuelTankL": 54,
              "consumption": 4.8,
              "co2": 123,
              "topSpeed": 163,
              "acceleration0100": 7.8,
              "tireSizeFront": "225/55 R17",
              "tireSizeRear": "225/55 R17",
              "rimSize": "6.5Jx17 ET49",
              "pcd": "5x112",
              "centerBore": 72.6,
              "offsetMin": 38,
              "offsetMax": 50,
              "wheelTorqueNm": 120,
              "threadSize": "M14x1.5",
              "boltType": "Tuerca",
              "tirePressureFrontBar": 2.0,
              "tirePressureRearBar": 2.1,
              "tirePressureFrontLoadedBar": 2.6,
              "tirePressureRearLoadedBar": 2.4,
              "publishedAt": null
            },
            {
              "slug": "1-0-tsi-110-cv",
              "name": "1.0 TSI 110 CV",
              "engineCode": "",
              "displacement": 999,
              "fuelType": "Gasolina",
              "powerHp": 110,
              "powerKw": 81,
              "torqueNm": 200,
              "transmission": "Manual 6v",
              "gears": 6,
              "driveType": "FWD",
              "lengthMm": 4890,
              "widthMm": 1878,
              "heightMm": 1513,
              "wheelbaseMm": 2839,
              "weightKg": 1561,
              "grossWeightKg": 2198,
              "trunkCapacityL": 485,
              "fuelTankL": 65,
              "consumption": 5.7,
              "co2": 121,
              "topSpeed": 197,
              "acceleration0100": 7.9,
              "tireSizeFront": "225/55 R17",
              "tireSizeRear": "225/55 R17",
              "rimSize": "6.5Jx17 ET38",
              "pcd": "5x112",
              "centerBore": 72.6,
              "offsetMin": 36,
              "offsetMax": 45,
              "wheelTorqueNm": 103,
              "threadSize": "M12x1.25",
              "boltType": "Tornillo",
              "tirePressureFrontBar": 2.5,
              "tirePressureRearBar": 2.3,
              "tirePressureFrontLoadedBar": 2.3,
              "tirePressureRearLoadedBar": 2.3,
              "publishedAt": null
            },
            {
              "slug": "1-6-phev-225-cv",
              "name": "1.6 PHEV 225 CV",
              "engineCode": "",
              "displacement": 1598,
              "fuelType": "Híbrido",
              "powerHp": 225,
              "powerKw": 165,
              "torqueNm": 360,
              "transmission": "Automático 8v",
              "gears": 8,
              "driveType": "FWD",
              "lengthMm": 4852,
              "widthMm": 1834,
              "heightMm": 1659,
              "wheelbaseMm": 2817,
              "weightKg": 1655,
              "grossWeightKg": 2092,
              "trunkCapacityL": 582,
              "fuelTankL": 61,
              "consumption": 1.6,
              "co2": 28,
              "topSpeed": 199,
              "acceleration0100": 9.4,
              "tireSizeFront": "225/55 R17",
              "tireSizeRear": "225/55 R17",
              "rimSize": "6.5Jx17 ET38",
              "pcd": "5x112",
              "centerBore": 72.6,
              "offsetMin": 40,
              "offsetMax": 52,
              "wheelTorqueNm": 110,
              "threadSize": "M14x1.5",
              "boltType": "Tuerca",
              "tirePressureFrontBar": 2.1,
              "tirePressureRearBar": 2.5,
              "tirePressureFrontLoadedBar": 2.6,
              "tirePressureRearLoadedBar": 2.4,
              "publishedAt": null
            }
          ]
        }
      ],
      "imageUrl": "https://upload.wikimedia.org/wikipedia/commons/thumb/7/77/Cupra_Tavascan_Leonberg_2024_IMG_0881.jpg/1280px-Cupra_Tavascan_Leonberg_2024_IMG_0881.jpg",
      "imagePageUrl": "https://en.wikipedia.org/wiki/Cupra_Tavascan",
      "imageTitle": "Cupra Tavascan",
      "imageLicense": "CC BY-SA / Wikimedia Commons (via Wikipedia page images)",
      "imageFetchedAt": "2026-04-01",
      "wheelSizeKnown": true
    },
    {
      "slug": "ateca",
      "name": "Ateca",
      "bodyType": "SUV",
      "segment": "Compacto",
      "years": "2020-2024",
      "current": false,
      "publishedAt": null,
      "generations": [
        {
          "slug": "2020-2024",
          "name": "Generación (2020-2024)",
          "yearStart": 2020,
          "yearEnd": 2024,
          "publishedAt": null,
          "variants": [
            {
              "slug": "2-0-tdi-200-cv",
              "name": "2.0 TDI 200 CV",
              "engineCode": "",
              "displacement": 1968,
              "fuelType": "Diésel",
              "powerHp": 200,
              "powerKw": 147,
              "torqueNm": 400,
              "transmission": "Automático DSG 7v",
              "gears": 7,
              "driveType": "FWD",
              "lengthMm": 4352,
              "widthMm": 1846,
              "heightMm": 1457,
              "wheelbaseMm": 2666,
              "weightKg": 1319,
              "grossWeightKg": 1861,
              "trunkCapacityL": 415,
              "fuelTankL": 45,
              "consumption": 5.5,
              "co2": 140,
              "topSpeed": 172,
              "acceleration0100": 10.6,
              "tireSizeFront": "205/55 R16",
              "tireSizeRear": "205/55 R16",
              "rimSize": "6.5Jx16 ET36",
              "pcd": "5x100",
              "centerBore": 56.1,
              "offsetMin": 42,
              "offsetMax": 52,
              "wheelTorqueNm": 110,
              "threadSize": "M12x1.25",
              "boltType": "Tornillo",
              "tirePressureFrontBar": 2.4,
              "tirePressureRearBar": 2.2,
              "tirePressureFrontLoadedBar": 2.6,
              "tirePressureRearLoadedBar": 2.4,
              "publishedAt": null
            },
            {
              "slug": "2-0-tdi-150-cv",
              "name": "2.0 TDI 150 CV",
              "engineCode": "",
              "displacement": 1968,
              "fuelType": "Diésel",
              "powerHp": 150,
              "powerKw": 110,
              "torqueNm": 360,
              "transmission": "Manual 6v",
              "gears": 6,
              "driveType": "FWD",
              "lengthMm": 4408,
              "widthMm": 1836,
              "heightMm": 1456,
              "wheelbaseMm": 2626,
              "weightKg": 1339,
              "grossWeightKg": 1633,
              "trunkCapacityL": 425,
              "fuelTankL": 51,
              "consumption": 5.0,
              "co2": 129,
              "topSpeed": 198,
              "acceleration0100": 8.3,
              "tireSizeFront": "205/55 R16",
              "tireSizeRear": "205/55 R16",
              "rimSize": "6.5Jx16 ET40",
              "pcd": "5x100",
              "centerBore": 56.1,
              "offsetMin": 40,
              "offsetMax": 51,
              "wheelTorqueNm": 140,
              "threadSize": "M12x1.5",
              "boltType": "Tornillo",
              "tirePressureFrontBar": 2.1,
              "tirePressureRearBar": 2.4,
              "tirePressureFrontLoadedBar": 2.6,
              "tirePressureRearLoadedBar": 2.6,
              "publishedAt": null
            },
            {
              "slug": "1-8-hybrid-122-cv",
              "name": "1.8 Hybrid 122 CV",
              "engineCode": "",
              "displacement": 1798,
              "fuelType": "Híbrido",
              "powerHp": 122,
              "powerKw": 90,
              "torqueNm": 142,
              "transmission": "Automático CVT",
              "gears": 0,
              "driveType": "FWD",
              "lengthMm": 4458,
              "widthMm": 1824,
              "heightMm": 1493,
              "wheelbaseMm": 2681,
              "weightKg": 1319,
              "grossWeightKg": 1708,
              "trunkCapacityL": 434,
              "fuelTankL": 46,
              "consumption": 4.6,
              "co2": 101,
              "topSpeed": 236,
              "acceleration0100": 7.7,
              "tireSizeFront": "205/55 R16",
              "tireSizeRear": "205/55 R16",
              "rimSize": "6.5Jx16 ET48",
              "pcd": "5x100",
              "centerBore": 56.1,
              "offsetMin": 43,
              "offsetMax": 56,
              "wheelTorqueNm": 103,
              "threadSize": "M14x1.5",
              "boltType": "Tuerca",
              "tirePressureFrontBar": 2.1,
              "tirePressureRearBar": 2.3,
              "tirePressureFrontLoadedBar": 2.4,
              "tirePressureRearLoadedBar": 2.3,
              "publishedAt": null
            }
          ]
        }
      ],
      "imageUrl": "https://upload.wikimedia.org/wikipedia/commons/thumb/b/bc/2017_SEAT_Ateca_Xcellence_1.4_Front.jpg/1280px-2017_SEAT_Ateca_Xcellence_1.4_Front.jpg",
      "imagePageUrl": "https://en.wikipedia.org/wiki/SEAT_Ateca",
      "imageTitle": "SEAT Ateca",
      "imageLicense": "CC BY-SA / Wikimedia Commons (via Wikipedia page images)",
      "imageFetchedAt": "2026-04-01",
      "wheelSizeKnown": true
    }
  ]
}